Swoop/DRU.py
Swoop/GenerateSwoop.py
Swoop/Swoop.py
Swoop/Swoop.py.jinja
Swoop/__init__.py
Swoop/default.dru
Swoop/eagle-6.5.0.dtd
Swoop/eagle-7.1.0.dtd
Swoop/eagle-7.2.0.dtd
Swoop/eagle-7.2.0.patched.dtd
Swoop/eagle-7.3.0.dtd
Swoop/eagle-7.4.0.dtd
Swoop/eagle-7.5.0-OLD.dtd
Swoop/eagle-7.6.0.dtd
Swoop/eagle-8.7.1.dtd
Swoop/eagle-9.0.0.dtd
Swoop/eagle-9.2.2.dtd
Swoop/eagle-9.2.2.patched.dtd
Swoop/eagle-swoop.dtd
Swoop/eagle.dtd.diff
Swoop/ext/Geometry.py
Swoop/ext/ShapelySwoop.py
Swoop/ext/Shapes.py
Swoop/ext/__init__.py
Swoop/ext/VectorFont/VectorFont.py
Swoop/ext/VectorFont/VectorFontData.py
Swoop/ext/VectorFont/VectorFontTypes.py
Swoop/ext/VectorFont/__init__.py
Swoop/ext/VectorFont/makeGeometry.py
Swoop/ext/VectorFont/makeLetters.py
Swoop/tools/CheckEagle.py
Swoop/tools/CleanupEagle.py
Swoop/tools/FixEagle.py
Swoop/tools/MergeLibrary.py
Swoop/tools/Relayer.py
Swoop/tools/SwoopTools.py
Swoop/tools/__init__.py
Swoop-0.6.5.dist-info/LICENSE.txt
Swoop-0.6.5.dist-info/METADATA
Swoop-0.6.5.dist-info/WHEEL
Swoop-0.6.5.dist-info/entry_points.txt
Swoop-0.6.5.dist-info/top_level.txt
Swoop-0.6.5.dist-info/RECORD
